README.md
setup.py
flyers/__init__.py
flyers/assets.py
flyers/concurrents.py
flyers/datetimes.py
flyers/emails.py
flyers/files.py
flyers/jsons.py
flyers/lists.py
flyers/logs.py
flyers/nets.py
flyers/strs.py
flyers/systems.py
flyers/txt.py
flyers.egg-info/PKG-INFO
flyers.egg-info/SOURCES.txt
flyers.egg-info/dependency_links.txt
flyers.egg-info/requires.txt
flyers.egg-info/top_level.txt
flyers/database/__init__.py
flyers/database/mysql.py
flyers/database/pool.py
flyers/spider/__init__.py
flyers/spider/seleniums.py
flyers/web/__init__.py
flyers/web/flasks.py
flyers/web/rest.py
test/test_database.py
test/test_date.py
test/test_log.py
test/test_nets.py
test/test_strs.py
test/test_systems.py