Metadata-Version: 2.1
Name: flyers
Version: 0.0.4
Summary: A collections of utils
Home-page: https://github.com/pushyzheng
Author: pushyzheng
Author-email: 1437876073@qq.com
License: UNKNOWN
Platform: UNKNOWN
